markdown_text_decorator/__init__.py
markdown_text_decorator/processors.py
markdown_text_decorator/sample.py
markdown_text_decorator/test.py
markdown_text_decorator-3.2.0.dist-info/LICENSE
markdown_text_decorator-3.2.0.dist-info/METADATA
markdown_text_decorator-3.2.0.dist-info/WHEEL
markdown_text_decorator-3.2.0.dist-info/top_level.txt
markdown_text_decorator-3.2.0.dist-info/RECORD
