Metadata-Version: 2.1
Name: markdown-text-decorator
Version: 3.2.0
Summary: Text Decorator Extension for Python-Markdown.
Author: Silver Bullet Software
Author-email: inq.sbs@gmail.com
Maintainer: sbs
Maintainer-email: inq.sbs@gmail.com
License: MIT
Classifier: Programming Language :: Python :: 3
Classifier: License :: OSI Approved :: MIT License
Classifier: Operating System :: OS Independent
Requires-Python: >=3.7
License-File: LICENSE
Requires-Dist: markdown (>=3)
